{
  "page_nr": 428,
  "image": {
    "width": 2479,
    "height": 3508,
    "url": "https://files.transkribus.eu/Get?fileType=view&id=ANMHFJZXHGMYSXWCMKKXRVOW",
    "file": "images/page_428.jpg"
  },
  "lines": [
    {
      "id": "tr_1_tl_1",
      "text": "Des vierd schlußred",
      "points": [
        [
          873.0,
          310.0
        ],
        [
          1050.0,
          219.0
        ],
        [
          1258.0,
          323.0
        ],
        [
          1354.0,
          246.0
        ],
        [
          1454.0,
          268.0
        ],
        [
          1570.0,
          234.0
        ],
        [
          1566.0,
          136.0
        ],
        [
          1400.0,
          187.0
        ],
        [
          1258.0,
          140.0
        ],
        [
          1203.0,
          178.0
        ],
        [
          1048.0,
          144.0
        ],
        [
          1009.0,
          178.0
        ],
        [
          922.0,
          119.0
        ],
        [
          867.0,
          138.0
        ]
      ],
      "bbox": {
        "x": 867.0,
        "y": 119.0,
        "w": 703.0,
        "h": 204.0
      }
    },
    {
      "id": "tr_1_tl_2",
      "text": "'6' 178",
      "points": [
        [
          1868.0,
          251.0
        ],
        [
          1970.0,
          255.0
        ],
        [
          1989.0,
          270.0
        ],
        [
          2025.0,
          240.0
        ],
        [
          2066.0,
          270.0
        ],
        [
          2102.0,
          257.0
        ],
        [
          2146.0,
          268.0
        ],
        [
          2146.0,
          210.0
        ],
        [
          2089.0,
          200.0
        ],
        [
          2008.0,
          144.0
        ],
        [
          1959.0,
          155.0
        ],
        [
          1930.0,
          149.0
        ],
        [
          1919.0,
          159.0
        ],
        [
          1902.0,
          153.0
        ],
        [
          1883.0,
          174.0
        ],
        [
          1866.0,
          172.0
        ]
      ],
      "bbox": {
        "x": 1866.0,
        "y": 144.0,
        "w": 280.0,
        "h": 126.0
      }
    },
    {
      "id": "tr_1_tl_3",
      "text": "Das wurde aber Dienen vieh men den schengen",
      "points": [
        [
          542.0,
          408.0
        ],
        [
          1122.0,
          372.0
        ],
        [
          1352.0,
          440.0
        ],
        [
          1679.0,
          380.0
        ],
        [
          2123.0,
          414.0
        ],
        [
          2121.0,
          323.0
        ],
        [
          1821.0,
          208.0
        ],
        [
          1643.0,
          355.0
        ],
        [
          954.0,
          319.0
        ],
        [
          835.0,
          234.0
        ],
        [
          748.0,
          300.0
        ],
        [
          538.0,
          268.0
        ]
      ],
      "bbox": {
        "x": 538.0,
        "y": 208.0,
        "w": 1585.0,
        "h": 232.0
      }
    },
    {
      "id": "tr_1_tl_4",
      "text": "Dann den christen, Hierumb an desem ont¬",
      "points": [
        [
          478.0,
          476.0
        ],
        [
          980.0,
          476.0
        ],
        [
          1099.0,
          531.0
        ],
        [
          1324.0,
          470.0
        ],
        [
          1432.0,
          521.0
        ],
        [
          1658.0,
          472.0
        ],
        [
          1866.0,
          542.0
        ],
        [
          1944.0,
          480.0
        ],
        [
          2089.0,
          495.0
        ],
        [
          2110.0,
          427.0
        ],
        [
          1881.0,
          391.0
        ],
        [
          1728.0,
          442.0
        ],
        [
          1349.0,
          442.0
        ],
        [
          1114.0,
          372.0
        ],
        [
          1052.0,
          427.0
        ],
        [
          839.0,
          376.0
        ],
        [
          476.0,
          440.0
        ]
      ],
      "bbox": {
        "x": 476.0,
        "y": 372.0,
        "w": 1634.0,
        "h": 170.0
      }
    },
    {
      "id": "tr_1_tl_5",
      "text": "zijn Chorunthern, am per cap: So haben creix ein",
      "points": [
        [
          508.0,
          627.0
        ],
        [
          608.0,
          578.0
        ],
        [
          710.0,
          625.0
        ],
        [
          765.0,
          570.0
        ],
        [
          910.0,
          601.0
        ],
        [
          1148.0,
          555.0
        ],
        [
          1545.0,
          561.0
        ],
        [
          1621.0,
          604.0
        ],
        [
          1883.0,
          570.0
        ],
        [
          1976.0,
          618.0
        ],
        [
          2038.0,
          557.0
        ],
        [
          2131.0,
          565.0
        ],
        [
          2108.0,
          502.0
        ],
        [
          1866.0,
          536.0
        ],
        [
          1640.0,
          474.0
        ],
        [
          1099.0,
          531.0
        ],
        [
          508.0,
          484.0
        ]
      ],
      "bbox": {
        "x": 508.0,
        "y": 474.0,
        "w": 1623.0,
        "h": 153.0
      }
    },
    {
      "id": "tr_1_tl_6",
      "text": "sein",
      "points": [
        [
          1150.0,
          606.0
        ],
        [
          1167.0,
          604.0
        ],
        [
          1177.0,
          612.0
        ],
        [
          1188.0,
          612.0
        ],
        [
          1192.0,
          608.0
        ],
        [
          1203.0,
          614.0
        ],
        [
          1237.0,
          610.0
        ],
        [
          1239.0,
          567.0
        ],
        [
          1228.0,
          567.0
        ],
        [
          1218.0,
          559.0
        ],
        [
          1194.0,
          565.0
        ],
        [
          1184.0,
          557.0
        ],
        [
          1152.0,
          557.0
        ]
      ],
      "bbox": {
        "x": 1150.0,
        "y": 557.0,
        "w": 89.0,
        "h": 57.0
      }
    },
    {
      "id": "tr_1_tl_7",
      "text": "gemeinschafft vande gsvesthafft, vnd sine ouck",
      "points": [
        [
          540.0,
          722.0
        ],
        [
          612.0,
          665.0
        ],
        [
          752.0,
          659.0
        ],
        [
          1577.0,
          708.0
        ],
        [
          1655.0,
          652.0
        ],
        [
          2063.0,
          657.0
        ],
        [
          2066.0,
          578.0
        ],
        [
          1983.0,
          618.0
        ],
        [
          1819.0,
          570.0
        ],
        [
          1536.0,
          618.0
        ],
        [
          1475.0,
          565.0
        ],
        [
          1284.0,
          557.0
        ],
        [
          1145.0,
          638.0
        ],
        [
          988.0,
          582.0
        ],
        [
          542.0,
          616.0
        ]
      ],
      "bbox": {
        "x": 540.0,
        "y": 557.0,
        "w": 1526.0,
        "h": 165.0
      }
    },
    {
      "id": "tr_1_tl_8",
      "text": "soo",
      "points": [
        [
          1938.0,
          680.0
        ],
        [
          1951.0,
          678.0
        ],
        [
          1966.0,
          691.0
        ],
        [
          1972.0,
          684.0
        ],
        [
          1998.0,
          684.0
        ],
        [
          2002.0,
          688.0
        ],
        [
          2006.0,
          684.0
        ],
        [
          2021.0,
          686.0
        ],
        [
          2029.0,
          680.0
        ],
        [
          2036.0,
          680.0
        ],
        [
          2034.0,
          648.0
        ],
        [
          2012.0,
          648.0
        ],
        [
          2004.0,
          652.0
        ],
        [
          1985.0,
          640.0
        ],
        [
          1970.0,
          640.0
        ],
        [
          1964.0,
          646.0
        ],
        [
          1936.0,
          644.0
        ]
      ],
      "bbox": {
        "x": 1936.0,
        "y": 640.0,
        "w": 100.0,
        "h": 51.0
      }
    },
    {
      "id": "tr_1_tl_9",
      "text": "ein yseelschafft Inn unserm houpt „ Christo „ will",
      "points": [
        [
          538.0,
          765.0
        ],
        [
          740.0,
          808.0
        ],
        [
          790.0,
          765.0
        ],
        [
          1014.0,
          799.0
        ],
        [
          1228.0,
          750.0
        ],
        [
          1318.0,
          805.0
        ],
        [
          1468.0,
          759.0
        ],
        [
          1606.0,
          799.0
        ],
        [
          2102.0,
          737.0
        ],
        [
          2104.0,
          669.0
        ],
        [
          1938.0,
          718.0
        ],
        [
          1732.0,
          665.0
        ],
        [
          1602.0,
          718.0
        ],
        [
          1352.0,
          669.0
        ],
        [
          1143.0,
          718.0
        ],
        [
          767.0,
          665.0
        ],
        [
          540.0,
          727.0
        ]
      ],
      "bbox": {
        "x": 538.0,
        "y": 665.0,
        "w": 1566.0,
        "h": 143.0
      }
    },
    {
      "id": "tr_1_tl_10",
      "text": "darneben vn abgeschlagen haben, das die diener",
      "points": [
        [
          538.0,
          856.0
        ],
        [
          1133.0,
          899.0
        ],
        [
          1201.0,
          850.0
        ],
        [
          1279.0,
          888.0
        ],
        [
          1381.0,
          837.0
        ],
        [
          1634.0,
          835.0
        ],
        [
          1692.0,
          886.0
        ],
        [
          1738.0,
          839.0
        ],
        [
          2136.0,
          837.0
        ],
        [
          2136.0,
          771.0
        ],
        [
          538.0,
          790.0
        ]
      ],
      "bbox": {
        "x": 538.0,
        "y": 771.0,
        "w": 1598.0,
        "h": 128.0
      }
    },
    {
      "id": "tr_1_tl_11",
      "text": "der kilchen gememach mit ein andern oder In¬",
      "points": [
        [
          533.0,
          941.0
        ],
        [
          644.0,
          997.0
        ],
        [
          714.0,
          931.0
        ],
        [
          1099.0,
          975.0
        ],
        [
          1152.0,
          933.0
        ],
        [
          1220.0,
          975.0
        ],
        [
          2138.0,
          922.0
        ],
        [
          2138.0,
          852.0
        ],
        [
          1862.0,
          837.0
        ],
        [
          1694.0,
          888.0
        ],
        [
          1460.0,
          848.0
        ],
        [
          1379.0,
          899.0
        ],
        [
          924.0,
          907.0
        ],
        [
          718.0,
          835.0
        ],
        [
          652.0,
          876.0
        ],
        [
          536.0,
          850.0
        ]
      ],
      "bbox": {
        "x": 533.0,
        "y": 835.0,
        "w": 1605.0,
        "h": 162.0
      }
    },
    {
      "id": "tr_1_tl_12",
      "text": "vnderheit, die Sacramenten, vswillen, wer diss",
      "points": [
        [
          555.0,
          1054.0
        ],
        [
          680.0,
          1020.0
        ],
        [
          767.0,
          1060.0
        ],
        [
          835.0,
          1012.0
        ],
        [
          1007.0,
          1065.0
        ],
        [
          1264.0,
          1016.0
        ],
        [
          1668.0,
          1060.0
        ],
        [
          1855.0,
          1001.0
        ],
        [
          2089.0,
          1026.0
        ],
        [
          2159.0,
          1005.0
        ],
        [
          2161.0,
          901.0
        ],
        [
          1386.0,
          975.0
        ],
        [
          935.0,
          931.0
        ],
        [
          716.0,
          941.0
        ],
        [
          642.0,
          997.0
        ],
        [
          555.0,
          956.0
        ]
      ],
      "bbox": {
        "x": 555.0,
        "y": 901.0,
        "w": 1606.0,
        "h": 164.0
      }
    },
    {
      "id": "tr_1_tl_13",
      "text": "ist zu allen geschriben, vnnd die nachgende wort",
      "points": [
        [
          544.0,
          1156.0
        ],
        [
          674.0,
          1164.0
        ],
        [
          742.0,
          1103.0
        ],
        [
          1058.0,
          1145.0
        ],
        [
          2138.0,
          1090.0
        ],
        [
          2138.0,
          1028.0
        ],
        [
          1968.0,
          1054.0
        ],
        [
          1885.0,
          1001.0
        ],
        [
          1804.0,
          1060.0
        ],
        [
          1396.0,
          1018.0
        ],
        [
          1330.0,
          1073.0
        ],
        [
          1247.0,
          1024.0
        ],
        [
          756.0,
          1060.0
        ],
        [
          546.0,
          1018.0
        ]
      ],
      "bbox": {
        "x": 544.0,
        "y": 1001.0,
        "w": 1594.0,
        "h": 163.0
      }
    },
    {
      "id": "tr_1_tl_14",
      "text": "Die erklerens so er spricht Dann wir will sind",
      "points": [
        [
          495.0,
          1262.0
        ],
        [
          767.0,
          1209.0
        ],
        [
          950.0,
          1288.0
        ],
        [
          1033.0,
          1211.0
        ],
        [
          1184.0,
          1260.0
        ],
        [
          1383.0,
          1201.0
        ],
        [
          2000.0,
          1226.0
        ],
        [
          2146.0,
          1177.0
        ],
        [
          2148.0,
          1092.0
        ],
        [
          1904.0,
          1148.0
        ],
        [
          1496.0,
          1105.0
        ],
        [
          1434.0,
          1156.0
        ],
        [
          1203.0,
          1126.0
        ],
        [
          1067.0,
          1177.0
        ],
        [
          982.0,
          1126.0
        ],
        [
          835.0,
          1171.0
        ],
        [
          761.0,
          1122.0
        ],
        [
          495.0,
          1179.0
        ]
      ],
      "bbox": {
        "x": 495.0,
        "y": 1092.0,
        "w": 1653.0,
        "h": 196.0
      }
    },
    {
      "id": "tr_1_tl_15",
      "text": "ein brot vnd ein lye Diswijl wir all eius brets",
      "points": [
        [
          525.0,
          1332.0
        ],
        [
          2085.0,
          1290.0
        ],
        [
          2142.0,
          1279.0
        ],
        [
          2144.0,
          1209.0
        ],
        [
          1870.0,
          1256.0
        ],
        [
          1016.0,
          1228.0
        ],
        [
          954.0,
          1284.0
        ],
        [
          822.0,
          1224.0
        ],
        [
          612.0,
          1269.0
        ],
        [
          527.0,
          1239.0
        ]
      ],
      "bbox": {
        "x": 525.0,
        "y": 1209.0,
        "w": 1619.0,
        "h": 123.0
      }
    },
    {
      "id": "tr_1_tl_16",
      "text": "theilhafftig sind, dan wir sijnd theilhafftig, zum ersten",
      "points": [
        [
          538.0,
          1428.0
        ],
        [
          799.0,
          1454.0
        ],
        [
          878.0,
          1407.0
        ],
        [
          1815.0,
          1379.0
        ],
        [
          1908.0,
          1420.0
        ],
        [
          2197.0,
          1366.0
        ],
        [
          2165.0,
          1230.0
        ],
        [
          2072.0,
          1318.0
        ],
        [
          1964.0,
          1277.0
        ],
        [
          1878.0,
          1326.0
        ],
        [
          1184.0,
          1341.0
        ],
        [
          1094.0,
          1296.0
        ],
        [
          1033.0,
          1345.0
        ],
        [
          941.0,
          1300.0
        ],
        [
          540.0,
          1347.0
        ]
      ],
      "bbox": {
        "x": 538.0,
        "y": 1230.0,
        "w": 1659.0,
        "h": 224.0
      }
    },
    {
      "id": "tr_1_tl_17",
      "text": "mit ein andern Des himelsthen brots Christi Jesu",
      "points": [
        [
          540.0,
          1496.0
        ],
        [
          978.0,
          1532.0
        ],
        [
          1154.0,
          1481.0
        ],
        [
          1447.0,
          1519.0
        ],
        [
          1738.0,
          1481.0
        ],
        [
          1942.0,
          1532.0
        ],
        [
          2184.0,
          1483.0
        ],
        [
          2170.0,
          1362.0
        ],
        [
          1912.0,
          1426.0
        ],
        [
          1817.0,
          1381.0
        ],
        [
          1645.0,
          1436.0
        ],
        [
          1012.0,
          1398.0
        ],
        [
          880.0,
          1466.0
        ],
        [
          542.0,
          1439.0
        ]
      ],
      "bbox": {
        "x": 540.0,
        "y": 1362.0,
        "w": 1644.0,
        "h": 170.0
      }
    },
    {
      "id": "tr_1_tl_18",
      "text": "vnd hernach bezugen wir vns solches wanhafftig¬",
      "points": [
        [
          533.0,
          1604.0
        ],
        [
          1492.0,
          1575.0
        ],
        [
          1564.0,
          1636.0
        ],
        [
          1634.0,
          1581.0
        ],
        [
          2202.0,
          1600.0
        ],
        [
          2202.0,
          1522.0
        ],
        [
          2142.0,
          1483.0
        ],
        [
          1955.0,
          1530.0
        ],
        [
          1638.0,
          1492.0
        ],
        [
          1358.0,
          1547.0
        ],
        [
          1171.0,
          1483.0
        ],
        [
          978.0,
          1532.0
        ],
        [
          695.0,
          1481.0
        ],
        [
          533.0,
          1528.0
        ]
      ],
      "bbox": {
        "x": 533.0,
        "y": 1481.0,
        "w": 1669.0,
        "h": 155.0
      }
    },
    {
      "id": "tr_1_tl_19",
      "text": "klich In den Sacramenten, Durch das Sacrament",
      "points": [
        [
          538.0,
          1681.0
        ],
        [
          863.0,
          1679.0
        ],
        [
          1020.0,
          1738.0
        ],
        [
          1128.0,
          1670.0
        ],
        [
          1626.0,
          1698.0
        ],
        [
          2055.0,
          1655.0
        ],
        [
          2204.0,
          1715.0
        ],
        [
          2206.0,
          1602.0
        ],
        [
          1906.0,
          1568.0
        ],
        [
          1562.0,
          1636.0
        ],
        [
          1488.0,
          1575.0
        ],
        [
          1264.0,
          1634.0
        ],
        [
          1048.0,
          1587.0
        ],
        [
          540.0,
          1596.0
        ]
      ],
      "bbox": {
        "x": 538.0,
        "y": 1568.0,
        "w": 1668.0,
        "h": 170.0
      }
    },
    {
      "id": "tr_1_tl_20",
      "text": "lich bret",
      "points": [
        [
          529.0,
          1772.0
        ],
        [
          561.0,
          1785.0
        ],
        [
          625.0,
          1785.0
        ],
        [
          642.0,
          1772.0
        ],
        [
          678.0,
          1787.0
        ],
        [
          722.0,
          1760.0
        ],
        [
          824.0,
          1819.0
        ],
        [
          869.0,
          1796.0
        ],
        [
          871.0,
          1679.0
        ],
        [
          771.0,
          1708.0
        ],
        [
          720.0,
          1706.0
        ],
        [
          701.0,
          1692.0
        ],
        [
          610.0,
          1734.0
        ],
        [
          572.0,
          1708.0
        ],
        [
          531.0,
          1715.0
        ]
      ],
      "bbox": {
        "x": 529.0,
        "y": 1679.0,
        "w": 342.0,
        "h": 140.0
      }
    },
    {
      "id": "tr_1_tl_21",
      "text": "Althamer",
      "points": [
        [
          1162.0,
          1902.0
        ],
        [
          1209.0,
          1912.0
        ],
        [
          1239.0,
          1883.0
        ],
        [
          1334.0,
          1889.0
        ],
        [
          1415.0,
          1864.0
        ],
        [
          1454.0,
          1881.0
        ],
        [
          1519.0,
          1868.0
        ],
        [
          1519.0,
          1821.0
        ],
        [
          1492.0,
          1819.0
        ],
        [
          1466.0,
          1794.0
        ],
        [
          1368.0,
          1813.0
        ],
        [
          1332.0,
          1791.0
        ],
        [
          1307.0,
          1806.0
        ],
        [
          1252.0,
          1800.0
        ],
        [
          1205.0,
          1819.0
        ],
        [
          1164.0,
          1806.0
        ]
      ],
      "bbox": {
        "x": 1162.0,
        "y": 1791.0,
        "w": 357.0,
        "h": 121.0
      }
    },
    {
      "id": "tr_1_tl_22",
      "text": "Als bringt nun her Doctor herfur dis grwisth",
      "points": [
        [
          538.0,
          1978.0
        ],
        [
          1719.0,
          2012.0
        ],
        [
          1840.0,
          1974.0
        ],
        [
          2002.0,
          2044.0
        ],
        [
          2074.0,
          1985.0
        ],
        [
          2216.0,
          2006.0
        ],
        [
          2216.0,
          1864.0
        ],
        [
          2061.0,
          1825.0
        ],
        [
          1696.0,
          1915.0
        ],
        [
          1517.0,
          1855.0
        ],
        [
          1062.0,
          1949.0
        ],
        [
          852.0,
          1940.0
        ],
        [
          737.0,
          1842.0
        ],
        [
          538.0,
          1887.0
        ]
      ],
      "bbox": {
        "x": 538.0,
        "y": 1825.0,
        "w": 1678.0,
        "h": 219.0
      }
    },
    {
      "id": "tr_1_tl_23",
      "text": "wort, Parcovia heissz ein geselschafft, Das ver¬",
      "points": [
        [
          531.0,
          2127.0
        ],
        [
          846.0,
          2074.0
        ],
        [
          1186.0,
          2110.0
        ],
        [
          1334.0,
          2059.0
        ],
        [
          1694.0,
          2129.0
        ],
        [
          1998.0,
          2059.0
        ],
        [
          2214.0,
          2078.0
        ],
        [
          2216.0,
          2006.0
        ],
        [
          2108.0,
          1976.0
        ],
        [
          2002.0,
          2044.0
        ],
        [
          1583.0,
          1972.0
        ],
        [
          1481.0,
          2014.0
        ],
        [
          1014.0,
          1987.0
        ],
        [
          941.0,
          2036.0
        ],
        [
          835.0,
          1998.0
        ],
        [
          533.0,
          2032.0
        ]
      ],
      "bbox": {
        "x": 531.0,
        "y": 1972.0,
        "w": 1685.0,
        "h": 157.0
      }
    },
    {
      "id": "tr_1_tl_24",
      "text": "nein ick Im nitt Das an vill exten denselbi¬",
      "points": [
        [
          538.0,
          2172.0
        ],
        [
          604.0,
          2210.0
        ],
        [
          1409.0,
          2155.0
        ],
        [
          2189.0,
          2193.0
        ],
        [
          2189.0,
          2093.0
        ],
        [
          2042.0,
          2059.0
        ],
        [
          1887.0,
          2121.0
        ],
        [
          1432.0,
          2068.0
        ],
        [
          1386.0,
          2104.0
        ],
        [
          1334.0,
          2059.0
        ],
        [
          999.0,
          2140.0
        ],
        [
          648.0,
          2095.0
        ],
        [
          538.0,
          2129.0
        ]
      ],
      "bbox": {
        "x": 538.0,
        "y": 2059.0,
        "w": 1651.0,
        "h": 151.0
      }
    },
    {
      "id": "tr_1_tl_25",
      "text": "gen verstand, oder bedutung hab. Ober Daruss",
      "points": [
        [
          529.0,
          2320.0
        ],
        [
          735.0,
          2274.0
        ],
        [
          827.0,
          2314.0
        ],
        [
          1420.0,
          2257.0
        ],
        [
          1683.0,
          2308.0
        ],
        [
          1966.0,
          2244.0
        ],
        [
          2202.0,
          2276.0
        ],
        [
          2172.0,
          2144.0
        ],
        [
          1955.0,
          2210.0
        ],
        [
          1230.0,
          2161.0
        ],
        [
          531.0,
          2225.0
        ]
      ],
      "bbox": {
        "x": 529.0,
        "y": 2144.0,
        "w": 1673.0,
        "h": 176.0
      }
    },
    {
      "id": "tr_1_tl_26",
      "text": "wirt uit volgen, Das es ouch hie muss haben",
      "points": [
        [
          531.0,
          2382.0
        ],
        [
          710.0,
          2416.0
        ],
        [
          878.0,
          2363.0
        ],
        [
          1851.0,
          2359.0
        ],
        [
          1923.0,
          2412.0
        ],
        [
          2112.0,
          2344.0
        ],
        [
          2229.0,
          2365.0
        ],
        [
          2231.0,
          2244.0
        ],
        [
          2146.0,
          2295.0
        ],
        [
          1974.0,
          2246.0
        ],
        [
          1810.0,
          2325.0
        ],
        [
          1513.0,
          2265.0
        ],
        [
          1354.0,
          2320.0
        ],
        [
          1271.0,
          2263.0
        ],
        [
          531.0,
          2323.0
        ]
      ],
      "bbox": {
        "x": 531.0,
        "y": 2244.0,
        "w": 1700.0,
        "h": 172.0
      }
    },
    {
      "id": "tr_1_tl_27",
      "text": "Denn In der ii Epist: zum Oferin: am dij cop:",
      "points": [
        [
          529.0,
          2510.0
        ],
        [
          978.0,
          2454.0
        ],
        [
          1177.0,
          2518.0
        ],
        [
          1417.0,
          2450.0
        ],
        [
          1526.0,
          2512.0
        ],
        [
          1683.0,
          2446.0
        ],
        [
          1764.0,
          2520.0
        ],
        [
          1851.0,
          2456.0
        ],
        [
          2078.0,
          2476.0
        ],
        [
          2223.0,
          2416.0
        ],
        [
          2104.0,
          2344.0
        ],
        [
          1834.0,
          2416.0
        ],
        [
          1432.0,
          2354.0
        ],
        [
          1207.0,
          2406.0
        ],
        [
          952.0,
          2365.0
        ],
        [
          867.0,
          2427.0
        ],
        [
          784.0,
          2378.0
        ],
        [
          714.0,
          2420.0
        ],
        [
          533.0,
          2388.0
        ]
      ],
      "bbox": {
        "x": 529.0,
        "y": 2344.0,
        "w": 1694.0,
        "h": 176.0
      }
    },
    {
      "id": "tr_1_tl_28",
      "text": "oder lesten, So paulus spricht Die gnad vnsers",
      "points": [
        [
          540.0,
          2558.0
        ],
        [
          788.0,
          2597.0
        ],
        [
          1366.0,
          2539.0
        ],
        [
          1734.0,
          2590.0
        ],
        [
          1849.0,
          2544.0
        ],
        [
          1932.0,
          2586.0
        ],
        [
          2246.0,
          2522.0
        ],
        [
          2248.0,
          2452.0
        ],
        [
          2202.0,
          2422.0
        ],
        [
          2002.0,
          2505.0
        ],
        [
          1844.0,
          2461.0
        ],
        [
          1764.0,
          2522.0
        ],
        [
          1685.0,
          2448.0
        ],
        [
          1526.0,
          2514.0
        ],
        [
          1415.0,
          2452.0
        ],
        [
          1179.0,
          2518.0
        ],
        [
          975.0,
          2452.0
        ],
        [
          542.0,
          2508.0
        ]
      ],
      "bbox": {
        "x": 540.0,
        "y": 2422.0,
        "w": 1708.0,
        "h": 175.0
      }
    },
    {
      "id": "tr_1_tl_29",
      "text": "hern Jesu Christi vnd lieben gets. vnd gemein¬",
      "points": [
        [
          533.0,
          2654.0
        ],
        [
          816.0,
          2714.0
        ],
        [
          922.0,
          2654.0
        ],
        [
          1111.0,
          2722.0
        ],
        [
          1241.0,
          2648.0
        ],
        [
          1386.0,
          2705.0
        ],
        [
          1460.0,
          2639.0
        ],
        [
          1940.0,
          2669.0
        ],
        [
          2066.0,
          2620.0
        ],
        [
          2210.0,
          2667.0
        ],
        [
          2214.0,
          2580.0
        ],
        [
          1570.0,
          2588.0
        ],
        [
          1364.0,
          2535.0
        ],
        [
          1298.0,
          2588.0
        ],
        [
          1192.0,
          2548.0
        ],
        [
          1120.0,
          2612.0
        ],
        [
          1031.0,
          2552.0
        ],
        [
          948.0,
          2601.0
        ],
        [
          880.0,
          2558.0
        ],
        [
          801.0,
          2612.0
        ],
        [
          722.0,
          2567.0
        ],
        [
          536.0,
          2599.0
        ]
      ],
      "bbox": {
        "x": 533.0,
        "y": 2535.0,
        "w": 1681.0,
        "h": 187.0
      }
    },
    {
      "id": "tr_1_tl_30",
      "text": "schafft des heilligen geists sig mit vich allen",
      "points": [
        [
          552.0,
          2762.0
        ],
        [
          1109.0,
          2750.0
        ],
        [
          1490.0,
          2814.0
        ],
        [
          1687.0,
          2733.0
        ],
        [
          2189.0,
          2758.0
        ],
        [
          2191.0,
          2667.0
        ],
        [
          2051.0,
          2644.0
        ],
        [
          1685.0,
          2684.0
        ],
        [
          1458.0,
          2639.0
        ],
        [
          1383.0,
          2705.0
        ],
        [
          1232.0,
          2678.0
        ],
        [
          1114.0,
          2720.0
        ],
        [
          920.0,
          2654.0
        ],
        [
          827.0,
          2712.0
        ],
        [
          557.0,
          2663.0
        ]
      ],
      "bbox": {
        "x": 552.0,
        "y": 2639.0,
        "w": 1639.0,
        "h": 175.0
      }
    },
    {
      "id": "tr_1_tl_31",
      "text": "stet ouch Das wortlij korceria vnd winstt",
      "points": [
        [
          538.0,
          2918.0
        ],
        [
          788.0,
          2911.0
        ],
        [
          912.0,
          2852.0
        ],
        [
          1218.0,
          2922.0
        ],
        [
          1320.0,
          2875.0
        ],
        [
          1434.0,
          2922.0
        ],
        [
          1694.0,
          2898.0
        ],
        [
          1772.0,
          2824.0
        ],
        [
          2187.0,
          2820.0
        ],
        [
          2189.0,
          2758.0
        ],
        [
          1891.0,
          2726.0
        ],
        [
          1577.0,
          2818.0
        ],
        [
          1073.0,
          2807.0
        ],
        [
          1007.0,
          2752.0
        ],
        [
          780.0,
          2816.0
        ],
        [
          542.0,
          2769.0
        ]
      ],
      "bbox": {
        "x": 538.0,
        "y": 2726.0,
        "w": 1651.0,
        "h": 196.0
      }
    },
    {
      "id": "tr_1_tl_32",
      "text": "1.",
      "points": [
        [
          2091.0,
          2922.0
        ],
        [
          2110.0,
          2922.0
        ],
        [
          2116.0,
          2916.0
        ],
        [
          2146.0,
          2932.0
        ],
        [
          2180.0,
          2932.0
        ],
        [
          2170.0,
          2809.0
        ],
        [
          2155.0,
          2807.0
        ],
        [
          2131.0,
          2820.0
        ],
        [
          2114.0,
          2818.0
        ],
        [
          2102.0,
          2833.0
        ],
        [
          2085.0,
          2837.0
        ]
      ],
      "bbox": {
        "x": 2085.0,
        "y": 2807.0,
        "w": 95.0,
        "h": 125.0
      }
    }
  ]
}